{"cameraMode":{"drawMode":0,"name":"Shaded","section":"Shading Mode"},"sceneLighting":true,"audioPlay":false,"sceneViewState":{"showFog":true,"showMaterialUpdate":false,"showSkybox":true,"showFlares":true,"showImageEffects":true,"showParticleSystems":true},"in2DMode":false,"pivot":{"x":-3.951185464859009,"y":-1.3015694618225098,"z":-9.401345252990723},"rotation":{"x":-0.1835910975933075,"y":-0.6675845980644226,"z":0.17509911954402924,"w":-0.7000138759613037},"size":5.959723472595215,"orthographic":false}